Metadata-Version: 2.2
Name: portal
Version: 3.7.3
Summary: Fast and reliable distributed systems in Python
Home-page: http://github.com/danijar/portal
Author: Danijar Hafner
Author-email: mail@danijar.com
Classifier: Intended Audience :: Science/Research
Classifier: License :: OSI Approved :: MIT License
Classifier: Programming Language :: Python :: 3
License-File: LICENSE
Requires-Dist: cloudpickle
Requires-Dist: msgpack
Requires-Dist: numpy
Requires-Dist: psutil
Dynamic: author
Dynamic: author-email
Dynamic: classifier
Dynamic: description
Dynamic: description-content-type
Dynamic: home-page
Dynamic: requires-dist
Dynamic: summary
